[{"al": "springschoolsportsmeeting2026", "name": "DSC_0524.JPG", "h": 3264, "w": 4928, "ct": 1777776747.1256993, "faces": []}, {"al": "springschoolsportsmeeting2026", "name": "DSC_0525.JPG", "h": 3264, "w": 4928, "ct": 1777776747.1416905, "faces": []}, {"al": "springschoolsportsmeeting2026", "name": "DSC_0526.JPG", "h": 3264, "w": 4928, "ct": 1777776747.1416905, "faces": [[2356, 192, 331, 469]]}, {"al": "springschoolsportsmeeting2026", "name": "DSC_0530.JPG", "h": 3264, "w": 4928, "ct": 1777776747.174335, "faces": []}, {"al": "springschoolsportsmeeting2026", "name": "DSC_0531.JPG", "h": 3264, "w": 4928, "ct": 1777776747.221402, "faces": []}, {"al": "springschoolsportsmeeting2026", "name": "DSC_0532.JPG", "h": 3264, "w": 4928, "ct": 1777776747.277324, "faces": []}, {"al": "springschoolsportsmeeting2026", "name": "DSC_0533.JPG", "h": 3264, "w": 4928, "ct": 1777776747.3478012, "faces": []}, {"al": "springschoolsportsmeeting2026", "name": "DSC_0534.JPG", "h": 3264, "w": 4928, "ct": 1777776747.371694, "faces": []}, {"al": "springschoolsportsmeeting2026", "name": "DSC_0536.JPG", "h": 3264, "w": 4928, "ct": 1777776747.3793423, "faces": []}, {"al": "springschoolsportsmeeting2026", "name": "DSC_0537.JPG", "h": 3264, "w": 4928, "ct": 1777776747.3955648, "faces": []}, {"al": "springschoolsportsmeeting2026", "name": "DSC_0538.JPG", "h": 3264, "w": 4928, "ct": 1777776747.4113698, "faces": []}, {"al": "springschoolsportsmeeting2026", "name": "DSC_0539.JPG", "h": 3264, "w": 4928, "ct": 1777776747.437869, "faces": []}, {"al": "springschoolsportsmeeting2026", "name": "DSC_0540.JPG", "h": 3264, "w": 4928, "ct": 1777776747.4503443, "faces": []}, {"al": "springschoolsportsmeeting2026", "name": "DSC_0541.JPG", "h": 3264, "w": 4928, "ct": 1777776747.4591813, "faces": []}, {"al": "springschoolsportsmeeting2026", "name": "DSC_0542.JPG", "h": 3264, "w": 4928, "ct": 1777776747.47497, "faces": []}, {"al": "springschoolsportsmeeting2026", "name": "DSC_0543.JPG", "h": 3264, "w": 4928, "ct": 1777776747.4909196, "faces": []}, {"al": "springschoolsportsmeeting2026", "name": "DSC_0544.JPG", "h": 3264, "w": 4928, "ct": 1777776747.506819, "faces": []}, {"al": "springschoolsportsmeeting2026", "name": "DSC_0545.JPG", "h": 3264, "w": 4928, "ct": 1777776747.5246632, "faces": []}, {"al": "springschoolsportsmeeting2026", "name": "DSC_0546.JPG", "h": 3264, "w": 4928, "ct": 1777776747.5385969, "faces": []}, {"al": "springschoolsportsmeeting2026", "name": "DSC_0547.JPG", "h": 3264, "w": 4928, "ct": 1777776747.5564613, "faces": []}, {"al": "springschoolsportsmeeting2026", "name": "DSC_0548.JPG", "h": 3264, "w": 4928, "ct": 1777776747.5859444, "faces": []}, {"al": "springschoolsportsmeeting2026", "name": "DSC_0549.JPG", "h": 3264, "w": 4928, "ct": 1777776747.6017334, "faces": []}, {"al": "springschoolsportsmeeting2026", "name": "DSC_0550.JPG", "h": 3264, "w": 4928, "ct": 1777776747.174335, "faces": []}, {"al": "springschoolsportsmeeting2026", "name": "IMG_3749.JPG", "h": 4000, "w": 6000, "ct": 1777776750.5429704, "faces": []}, {"al": "springschoolsportsmeeting2026", "name": "IMG_3750.JPG", "h": 4000, "w": 6000, "ct": 1777776748.3353212, "faces": []}, {"al": "springschoolsportsmeeting2026", "name": "IMG_3753.JPG", "h": 4000, "w": 6000, "ct": 1777776748.4171882, "faces": []}, {"al": "springschoolsportsmeeting2026", "name": "IMG_3754.JPG", "h": 4000, "w": 6000, "ct": 1777776748.4312105, "faces": []}, {"al": "springschoolsportsmeeting2026", "name": "IMG_3755.JPG", "h": 4000, "w": 6000, "ct": 1777776748.4629002, "faces": []}, {"al": "springschoolsportsmeeting2026", "name": "IMG_3756.JPG", "h": 4000, "w": 6000, "ct": 1777776748.4788723, "faces": []}, {"al": "springschoolsportsmeeting2026", "name": "IMG_3757.JPG", "h": 4000, "w": 6000, "ct": 1777776748.5006773, "faces": []}, {"al": "springschoolsportsmeeting2026", "name": "IMG_3758.JPG", "h": 4000, "w": 6000, "ct": 1777776748.510599, "faces": []}, {"al": "springschoolsportsmeeting2026", "name": "IMG_3759.JPG", "h": 4000, "w": 6000, "ct": 1777776748.5266473, "faces": []}, {"al": "springschoolsportsmeeting2026", "name": "IMG_3760.JPG", "h": 4000, "w": 6000, "ct": 1777776748.5584655, "faces": []}, {"al": "springschoolsportsmeeting2026", "name": "IMG_3762.JPG", "h": 4000, "w": 6000, "ct": 1777776748.573768, "faces": []}, {"al": "springschoolsportsmeeting2026", "name": "IMG_3763.JPG", "h": 4000, "w": 6000, "ct": 1777776748.601097, "faces": []}, {"al": "springschoolsportsmeeting2026", "name": "IMG_3764.JPG", "h": 4000, "w": 6000, "ct": 1777776748.6209016, "faces": []}, {"al": "springschoolsportsmeeting2026", "name": "IMG_3765.JPG", "h": 4000, "w": 6000, "ct": 1777776748.6529205, "faces": []}, {"al": "springschoolsportsmeeting2026", "name": "IMG_3769.JPG", "h": 4000, "w": 6000, "ct": 1777776748.735989, "faces": []}, {"al": "springschoolsportsmeeting2026", "name": "IMG_3770.JPG", "h": 4000, "w": 6000, "ct": 1777776748.7610788, "faces": []}, {"al": "springschoolsportsmeeting2026", "name": "IMG_3771.JPG", "h": 4000, "w": 6000, "ct": 1777776747.712691, "faces": []}, {"al": "springschoolsportsmeeting2026", "name": "IMG_3772.JPG", "h": 4000, "w": 6000, "ct": 1777776747.7349617, "faces": []}, {"al": "springschoolsportsmeeting2026", "name": "IMG_3773.JPG", "h": 4000, "w": 6000, "ct": 1777776747.808136, "faces": []}, {"al": "springschoolsportsmeeting2026", "name": "IMG_3774.JPG", "h": 4000, "w": 6000, "ct": 1777776747.8559241, "faces": []}, {"al": "springschoolsportsmeeting2026", "name": "IMG_3775.JPG", "h": 4000, "w": 6000, "ct": 1777776747.8717551, "faces": []}, {"al": "springschoolsportsmeeting2026", "name": "IMG_3776.JPG", "h": 4000, "w": 6000, "ct": 1777776747.903536, "faces": []}, {"al": "springschoolsportsmeeting2026", "name": "IMG_3777.JPG", "h": 4000, "w": 6000, "ct": 1777776747.9193537, "faces": []}, {"al": "springschoolsportsmeeting2026", "name": "IMG_3778.JPG", "h": 4000, "w": 6000, "ct": 1777776747.9352596, "faces": []}, {"al": "springschoolsportsmeeting2026", "name": "IMG_3779.JPG", "h": 4000, "w": 6000, "ct": 1777776747.950999, "faces": []}, {"al": "springschoolsportsmeeting2026", "name": "IMG_3780.JPG", "h": 4000, "w": 6000, "ct": 1777776747.9669936, "faces": []}, {"al": "springschoolsportsmeeting2026", "name": "IMG_3781.JPG", "h": 4000, "w": 6000, "ct": 1777776748.2856755, "faces": []}]